MANIFEST.in
REQUIREMENTS
distribute_setup.py
setup.py
src/Markdoc.egg-info/PKG-INFO
src/Markdoc.egg-info/SOURCES.txt
src/Markdoc.egg-info/dependency_links.txt
src/Markdoc.egg-info/entry_points.txt
src/Markdoc.egg-info/requires.txt
src/Markdoc.egg-info/top_level.txt
src/markdoc/__init__.py
src/markdoc/builder.py
src/markdoc/cache.py
src/markdoc/config.py
src/markdoc/directories.py
src/markdoc/exc.py
src/markdoc/render.py
src/markdoc/server.py
src/markdoc/templates.py
src/markdoc/wsgi.py
src/markdoc/cli/__init__.py
src/markdoc/cli/commands.py
src/markdoc/cli/main.py
src/markdoc/cli/parser.py
src/markdoc/static/default-static/media/css/pygments.css
src/markdoc/static/default-static/media/css/style.css
src/markdoc/static/default-static/media/sass/_layout.sass
src/markdoc/static/default-static/media/sass/_typography.sass
src/markdoc/static/default-static/media/sass/style.sass
src/markdoc/static/default-templates/404.html
src/markdoc/static/default-templates/base.html
src/markdoc/static/default-templates/document.html
src/markdoc/static/default-templates/listing.html
src/markdoc/static/default-templates/macros/crumbs
src/markdoc/static/default-templates/macros/html
src/markdoc/static/default-templates/markdoc-default/404.html
src/markdoc/static/default-templates/markdoc-default/base.html
src/markdoc/static/default-templates/markdoc-default/document.html
src/markdoc/static/default-templates/markdoc-default/listing.html