Metadata-Version: 1.0
Name: Markdoc
Version: 0.6.4
Summary: A lightweight Markdown-based wiki build tool.
Home-page: http://github.com/zacharyvoase/markdoc
Author: Zachary Voase
Author-email: zacharyvoase@me.com
License: UNKNOWN
Platform: UNKNOWN
